Metadata-Version: 2.1
Name: sphinx-desktop
Version: 20240301
Summary: Open sphinx:// links on your desktop.
Author: Nate Skulic, MetaCompany
Requires-Python: >=3.6
Requires-Dist: toml
Provides-Extra: build
Requires-Dist: build; extra == "build"
Requires-Dist: pex; extra == "build"
Provides-Extra: test
Requires-Dist: pytest; extra == "test"
Requires-Dist: pytest-cov~=3.0.0; extra == "test"
Provides-Extra: documents
Requires-Dist: sphinx; extra == "documents"
Requires-Dist: sphinx-better-theme; extra == "documents"
Requires-Dist: myst-parser; extra == "documents"
Requires-Dist: markdown-it-py[linkify,plugins]; extra == "documents"
